{"cameraMode":{"drawMode":0,"name":"Shaded","section":"Shading Mode"},"sceneLighting":false,"audioPlay":false,"sceneViewState":{"showFog":true,"showMaterialUpdate":false,"showSkybox":false,"showFlares":true,"showImageEffects":true,"showParticleSystems":true},"in2DMode":false,"pivot":{"x":1.6901676654815674,"y":-0.8701812028884888,"z":13.081640243530274},"rotation":{"x":-0.036297306418418887,"y":-0.01589237153530121,"z":0.0005775539902970195,"w":-0.9992186427116394},"size":22.63681983947754,"orthographic":false}